phoenixnebula/__init__.py
phoenixnebula/phoenixnebula.py
phoenixnebula_cli-1.0.3.dist-info/licenses/LICENSE
phoenixnebula_cli-1.0.3.dist-info/METADATA
phoenixnebula_cli-1.0.3.dist-info/WHEEL
phoenixnebula_cli-1.0.3.dist-info/entry_points.txt
phoenixnebula_cli-1.0.3.dist-info/top_level.txt
phoenixnebula_cli-1.0.3.dist-info/RECORD
