Metadata-Version: 2.4
Name: phoenixnebula-cli
Version: 1.0.3
Summary: A feature-rich, customizable Unix shell with themes and job control
Home-page: https://github.com/SysTechSalihY/phoenixnebula
Author: Salih
Author-email: salihyilboga98@gmail.com
License: MIT
Project-URL: Bug Tracker, https://github.com/SysTechSalihY/phoenixnebula/issues
Project-URL: Documentation, https://github.com/SysTechSalihY/phoenixnebula
Project-URL: Source Code, https://github.com/SysTechSalihY/phoenixnebula
Keywords: shell terminal bash cli interactive
Classifier: Programming Language :: Python :: 3
Classifier: Programming Language :: Python :: 3.7
Classifier: Programming Language :: Python :: 3.8
Classifier: Programming Language :: Python :: 3.9
Classifier: Programming Language :: Python :: 3.10
Classifier: Programming Language :: Python :: 3.11
Classifier: License :: OSI Approved :: MIT License
Classifier: Operating System :: POSIX :: Linux
Classifier: Operating System :: MacOS
Classifier: Operating System :: POSIX :: BSD
Classifier: Environment :: Console
Classifier: Intended Audience :: Developers
Classifier: Intended Audience :: System Administrators
Classifier: Topic :: System :: Shells
Requires-Python: >=3.7
License-File: LICENSE
Dynamic: author
Dynamic: author-email
Dynamic: classifier
Dynamic: description
Dynamic: description-content-type
Dynamic: home-page
Dynamic: keywords
Dynamic: license-file
Dynamic: project-url
Dynamic: requires-python
Dynamic: summary
